tiamat_justice/__init__.py
tiamat_justice/readers/__init__.py
tiamat_justice/readers/bigtiff.py
tiamat_justice/readers/deformation.py
tiamat_justice/readers/hdf5/__init__.py
tiamat_justice/readers/hdf5/bda.py
tiamat_justice/readers/hdf5/fa.py
tiamat_justice/readers/zarr/__init__.py
tiamat_justice/readers/zarr/bda.py
tiamat_justice/transformers/__init__.py
tiamat_justice/transformers/meta.py
tiamat_justice/transformers/pli/geometric.py
tiamat_justice/transformers/pli/normalization.py
tiamat_justice-0.1.11.dist-info/licenses/LICENSE
tiamat_justice-0.1.11.dist-info/METADATA
tiamat_justice-0.1.11.dist-info/WHEEL
tiamat_justice-0.1.11.dist-info/top_level.txt
tiamat_justice-0.1.11.dist-info/RECORD
