Metadata-Version: 2.4
Name: tiamat-justice
Version: 0.1.11
Summary: tiamat - Jülich Data Storage and Image Conversion Extension
Author-email: "Big Data Analytics Group, Forschungszentrum Juelich, Institute of Neuroscience and Medicine (INM-1)" <inm1-bda@fz-juelich.de>
License: 
Project-URL: homepage, https://www.fz-juelich.de/de/inm/inm-1
Project-URL: documentation, https://jugit.fz-juelich.de/inm-1/bda/software/data_access/tiamat/tiamat-justice/-/blob/master/README.md?ref_type=heads
Project-URL: repository, https://jugit.fz-juelich.de/inm-1/bda/software/data_access/tiamat/tiamat-justice.git
Classifier: Programming Language :: Python :: 3
Classifier: Programming Language :: Python :: 3 :: Only
Classifier: Programming Language :: Python :: 3.10
Classifier: Programming Language :: Python :: 3.11
Classifier: Programming Language :: Python :: 3.12
Classifier: License :: OSI Approved :: MIT License
Classifier: Operating System :: POSIX :: Linux
Classifier: Topic :: Scientific/Engineering
Requires-Python: >=3.10
License-File: LICENSE
Requires-Dist: tiamat-python==0.1.10
Requires-Dist: pytiff==0.8.4
Requires-Dist: h5py
Provides-Extra: dev
Requires-Dist: autopep8; extra == "dev"
Requires-Dist: flake8; extra == "dev"
Requires-Dist: pytest; extra == "dev"
Provides-Extra: zarr
Requires-Dist: zarr>=3.1.1; extra == "zarr"
Dynamic: license-file
